cumulus_library/.sqlfluff
cumulus_library/__init__.py
cumulus_library/base_utils.py
cumulus_library/cli.py
cumulus_library/cli_parser.py
cumulus_library/const.py
cumulus_library/db_config.py
cumulus_library/enums.py
cumulus_library/errors.py
cumulus_library/log_utils.py
cumulus_library/module_allowlist.json
cumulus_library/study_manifest.py
cumulus_library/actions/builder.py
cumulus_library/actions/cleaner.py
cumulus_library/actions/exporter.py
cumulus_library/actions/file_generator.py
cumulus_library/actions/importer.py
cumulus_library/actions/uploader.py
cumulus_library/apis/__init__.py
cumulus_library/apis/loinc.py
cumulus_library/apis/umls.py
cumulus_library/builders/README.md
cumulus_library/builders/base_table_builder.py
cumulus_library/builders/counts.py
cumulus_library/builders/protected_table_builder.py
cumulus_library/builders/psm_builder.py
cumulus_library/builders/psmpy_lite.py
cumulus_library/builders/valueset_builder.py
cumulus_library/builders/reference_sql/psm.sql
cumulus_library/builders/statistics_templates/count.sql.jinja
cumulus_library/builders/statistics_templates/counts_templates.py
cumulus_library/builders/statistics_templates/psm_create_covariate_table.sql.jinja
cumulus_library/builders/statistics_templates/psm_distinct_ids.sql.jinja
cumulus_library/builders/statistics_templates/psm_templates.py
cumulus_library/builders/valueset/additional_rules_builder.py
cumulus_library/builders/valueset/lookup_drug_from_ingredient_rules.tsv
cumulus_library/builders/valueset/rxnorm_valueset_builder.py
cumulus_library/builders/valueset/static_builder.py
cumulus_library/builders/valueset/umls.py
cumulus_library/builders/valueset/valueset_utils.py
cumulus_library/builders/valueset/vsac.py
cumulus_library/builders/valueset/template_sql/create_included_keywords.sql.jinja
cumulus_library/builders/valueset/template_sql/create_keyword_annotated_table.sql.jinja
cumulus_library/builders/valueset/template_sql/create_search_rules_descriptions.sql.jinja
cumulus_library-5.1.1.dist-info/entry_points.txt
cumulus_library-5.1.1.dist-info/licenses/LICENSE
cumulus_library-5.1.1.dist-info/WHEEL
cumulus_library-5.1.1.dist-info/METADATA
cumulus_library-5.1.1.dist-info/RECORD
