Metadata-Version: 2.4
Name: cumulus-library
Version: 5.1.1
Summary: Clinical study SQL generation for data derived from bulk FHIR
Keywords: FHIR,SQL,Health Informatics
Requires-Python: >= 3.11
License-Expression: Apache-2.0
Classifier: Operating System :: OS Independent
Classifier: Programming Language :: Python :: 3
Classifier: Topic :: Software Development :: Libraries :: Python Modules
License-File: LICENSE
Requires-Dist: awswrangler >= 3.11, < 4
Requires-Dist: cumulus-fhir-support >= 1.6
Requires-Dist: duckdb >= 1.4.1
Requires-Dist: Jinja2 > 3
Requires-Dist: pandas <3, >=2.1.3
Requires-Dist: platformdirs
Requires-Dist: pyarrow >= 11.0
Requires-Dist: pyathena >= 2.23
Requires-Dist: pytablewriter >= 1.2
Requires-Dist: requests >= 2.28
Requires-Dist: rich >= 13.2
Requires-Dist: scipy >= 1.16
Requires-Dist: scikit-learn >= 1.7
Requires-Dist: sqlfluff  >= 3
Requires-Dist: sqlparse >0.4
Requires-Dist: ruff < 0.15 ; extra == "dev"
Requires-Dist: pre-commit ; extra == "dev"
Requires-Dist: freezegun ; extra == "test"
Requires-Dist: pytest ; extra == "test"
Requires-Dist: pytest-cov ; extra == "test"
Requires-Dist: pytest-xdist ; extra == "test"
Requires-Dist: responses ; extra == "test"
Project-URL: Documentation, https://docs.smarthealthit.org/cumulus/library/
Project-URL: Home, https://smarthealthit.org/cumulus/
Project-URL: Source, https://github.com/smart-on-fhir/cumulus-library
Provides-Extra: dev
Provides-Extra: test
